[
  {
    "especializacion": "Oftalmologo",
    "pacientesAsignados": [
      {
        "Enfermedad": "Bronquitis",
        "Sintomas": "dolor de garganta",
        "planDeControl": {
          "Enfermedad": "Dolor de Garganta",
          "Tiempo": 10,
          "Tratamientos": [
            {
              "type": "DatoNumerico",
              "properties": {
                "datoNumerico": 0.0,
                "descripcion": "Tomar temperatura"
              }
            },
            {
              "type": "DatoBoolean",
              "properties": {
                "datoBoolean": false,
                "descripcion": "Tomar Pastilla"
              }
            }
          ]
        },
        "FindelTratamiento": "24-jun.-2022",
        "PrincipiodelTratamiento": "14-jun.-2022",
        "historial": [],
        "password": "contra1",
        "user": "Pablo",
        "id": 1
      }
    ],
    "password": "contra3",
    "user": "Fernando",
    "id": 3
  },
  {
    "especializacion": "Pediatra",
    "pacientesAsignados": [],
    "password": "contra33",
    "user": "Julio",
    "id": 4
  }
]