[
  {
    "Enfermedad": "Bronquitis",
    "Sintomas": "dolor de garganta",
    "altamedica": false,
    "planDeControl": {
      "Enfermedad": "Dolor de Garganta",
      "Tiempo": 10,
      "Tratamientos": [
        {
          "type": "DatoNumerico",
          "properties": {
            "datoNumerico": 37.0,
            "descripcion": "Tomar temperatura"
          }
        },
        {
          "type": "DatoBoolean",
          "properties": {
            "datoBoolean": true,
            "descripcion": "Tomar Pastilla"
          }
        }
      ]
    },
    "FindelTratamiento": "24-jun.-2022",
    "PrincipiodelTratamiento": "14-jun.-2022",
    "historial": [
      {
        "fecha": "15-jun.-2022",
        "completado": false
      }
    ],
    "password": "contra1",
    "user": "Pablo",
    "id": 1
  },
  {
    "Enfermedad": "Dolor de Garganta",
    "Sintomas": "dolor de garganta cuando trago",
    "altamedica": false,
    "historial": [],
    "password": "contra11",
    "user": "Juan",
    "id": 2
  }
]